{
  "CustomName": "prod",
  "Name": "File Group",
  "Outputs": [
    {
      "ContainerSettings": {
        "Container": "MOV",
        "MovSettings": {
          "ClapAtom": "EXCLUDE",
          "CslgAtom": "INCLUDE",
          "PaddingControl": "OMNEON",
          "Reference": "SELF_CONTAINED",
          "Mpeg2FourCCControl": "MPEG"
        }
      },
      "VideoDescription": {
        "Width": 0,
        "ScalingBehavior": "DEFAULT",
        "Height": 0,
        "VideoPreprocessors": {
          "Deinterlacer": {
            "Algorithm": "INTERPOLATE",
            "Mode": "DEINTERLACE",
            "Control": "NORMAL"
          }
        },
        "TimecodeInsertion": "PIC_TIMING_SEI",
        "AntiAlias": "ENABLED",
        "Sharpness": 50,
        "CodecSettings": {
          "Codec": "H_264",
          "H264Settings": {
            "InterlaceMode": "PROGRESSIVE",
            "NumberReferenceFrames": 3,
            "Syntax": "DEFAULT",
            "Softness": 0,
            "GopClosedCadence": 1,
            "GopSize": 2,
            "Slices": 1,
            "GopBReference": "DISABLED",
            "MaxBitrate": 2000000,
            "SlowPal": "DISABLED",
            "SpatialAdaptiveQuantization": "ENABLED",
            "TemporalAdaptiveQuantization": "ENABLED",
            "FlickerAdaptiveQuantization": "DISABLED",
            "EntropyEncoding": "CABAC",
            "FramerateControl": "INITIALIZE_FROM_SOURCE",
            "RateControlMode": "QVBR",
            "QvbrSettings": {
              "QvbrQualityLevel": 7,
              "QvbrQualityLevelFineTune": 0
            },
            "CodecProfile": "HIGH",
            "Telecine": "NONE",
            "MinIInterval": 0,
            "AdaptiveQuantization": "HIGH",
            "CodecLevel": "AUTO",
            "FieldEncoding": "PAFF",
            "SceneChangeDetect": "ENABLED",
            "QualityTuningLevel": "SINGLE_PASS",
            "FramerateConversionAlgorithm": "DUPLICATE_DROP",
            "UnregisteredSeiTimecode": "ENABLED",
            "GopSizeUnits": "SECONDS",
            "ParControl": "INITIALIZE_FROM_SOURCE",
            "NumberBFramesBetweenReferenceFrames": 2,
            "RepeatPps": "DISABLED"
          }
        },
        "AfdSignaling": "NONE",
        "DropFrameTimecode": "ENABLED",
        "RespondToAfd": "NONE",
        "ColorMetadata": "INSERT"
      },
      "AudioDescriptions": [
        {
          "AudioTypeControl": "FOLLOW_INPUT",
          "AudioSourceName": "##PLACEHOLDER",
          "CodecSettings": {
            "Codec": "AAC",
            "AacSettings": {
              "AudioDescriptionBroadcasterMix": "NORMAL",
              "Bitrate": 96000,
              "RateControlMode": "CBR",
              "CodecProfile": "LC",
              "CodingMode": "CODING_MODE_2_0",
              "RawFormat": "NONE",
              "SampleRate": 48000,
              "Specification": "MPEG4"
            }
          },
          "LanguageCodeControl": "FOLLOW_INPUT"
        }
      ],
      "Extension": "mp4"
    }
  ],
  "OutputGroupSettings": {
    "Type": "FILE_GROUP_SETTINGS",
    "FileGroupSettings": {
      "Destination": "##PLACEHOLDER"
    }
  }
}
